price_forecast/__init__.py
price_forecast/data_quality_reference.py
price_forecast/data_quality_tools.py
price_forecast/data_scrapper.py
price_forecast/drive_connection.py
price_forecast/etl.py
price_forecast/forecaster.py
price_forecast/misc.py
price_forecast/queries_templates.py
price_forecast/viz_tools.py
pixie_price_forecast-3.3.0.dist-info/METADATA
pixie_price_forecast-3.3.0.dist-info/WHEEL
pixie_price_forecast-3.3.0.dist-info/top_level.txt
pixie_price_forecast-3.3.0.dist-info/RECORD
