Metadata-Version: 2.1
Name: pixie-price-forecast
Version: 3.3.0
Summary: Price forecast tools.
Home-page: https://github.mpi-internal.com/joseangel-mielgo/pixie-price-forecast
Author: Pixie Pixel
Author-email: joseangel.mielgo@adevinta.com
License: UNKNOWN
Project-URL: Bug Tracker, https://github.mpi-internal.com/joseangel-mielgo/pixie-price-forecast
Platform: UNKNOWN
Classifier: Programming Language :: Python :: 3
Classifier: License :: OSI Approved :: MIT License
Classifier: Operating System :: OS Independent
Requires-Python: >=3.6
Requires-Dist: pandas
Requires-Dist: numpy
Requires-Dist: sqlalchemy
Requires-Dist: sshtunnel
Requires-Dist: matplotlib
Requires-Dist: statsmodels
Requires-Dist: scikit-learn
Requires-Dist: tensorflow
Requires-Dist: requests
Requires-Dist: beautifulsoup4
Requires-Dist: python-dateutil
